{"U0PKNFNHG":{"data":[{"timestamp":"2019-10-11T02:40:37.120Z","note":"My note from DM","color":"yellow"},{"timestamp":"2019-10-11T02:39:04.302Z","note":"This is my note from App Home!","color":"blue"},{"timestamp":"2019-10-11T02:36:37.247Z","note":"moooooooo :cow:","color":"yellow"},{"timestamp":"2019-10-11T02:38:27.842Z","note":"This is my note from DM","color":"yellow"},{"timestamp":"2019-10-11T02:38:31.086Z","note":"This is my note from DM","color":"yellow"},{"timestamp":"2019-10-11T02:40:34.360Z","note":"This is my note from DM","color":"yellow"},{"timestamp":"2019-10-11T02:46:34.937Z","note":"This is my note from DM","color":"yellow"}]}}